{
  "formatVersion": 1,
  "database": {
    "version": 1,
    "identityHash": "5e20f871cb2ff00768764fe2b443cce0",
    "entities": [
      {
        "tableName": "playlist",
        "createSql": "CREATE TABLE IF NOT EXISTS `${TABLE_NAME}` (`id` TEXT NOT NULL, `channelTitle` TEXT NOT NULL, `title` TEXT NOT NULL, `description` TEXT NOT NULL, `thumbnailUrl` TEXT NOT NULL, `publishedAt` INTEGER NOT NULL, PRIMARY KEY(`id`))",
        "fields": [
          {
            "fieldPath": "id",
            "columnName": "id",
            "affinity": "TEXT",
            "notNull": true
          },
          {
            "fieldPath": "channelTitle",
            "columnName": "channelTitle",
            "affinity": "TEXT",
            "notNull": true
          },
          {
            "fieldPath": "title",
            "columnName": "title",
            "affinity": "TEXT",
            "notNull": true
          },
          {
            "fieldPath": "description",
            "columnName": "description",
            "affinity": "TEXT",
            "notNull": true
          },
          {
            "fieldPath": "thumbnailUrl",
            "columnName": "thumbnailUrl",
            "affinity": "TEXT",
            "notNull": true
          },
          {
            "fieldPath": "publishedAt",
            "columnName": "publishedAt",
            "affinity": "INTEGER",
            "notNull": true
          }
        ],
        "primaryKey": {
          "autoGenerate": false,
          "columnNames": [
            "id"
          ]
        },
        "indices": [],
        "foreignKeys": []
      }
    ],
    "views": [],
    "setupQueries": [
      "CREATE TABLE IF NOT EXISTS room_master_table (id INTEGER PRIMARY KEY,identity_hash TEXT)",
      "INSERT OR REPLACE INTO room_master_table (id,identity_hash) VALUES(42, '5e20f871cb2ff00768764fe2b443cce0')"
    ]
  }
}